{
	"required": true,
	"minVersion": "0.8",
	"package": "io.github.fourmisain.dyeallthethings.mixin",
	"compatibilityLevel": "JAVA_${java_version}",
	"plugin": "io.github.fourmisain.dyeallthethings.MixinPlugin",
	"mixins": [
		"MinecraftServerMixin",
		"RecipeManagerMixin",
		"RecipeSerializersMixin",
		"access.CauldronInteractionDispatcherAccessor",
		"trident.ThrownTridentMixin"
	],
	"client": [
		"BasicItemModelMixin",
		"EquipmentRendererMixin",
		"NoDataSpecialModelRendererMixin",
		"shield.ShieldSpecialRendererMixin",
		"trident.ThrownTridentRendererMixin",
		"trident.ThrownTridentRenderStateMixin",
		"trident.TridentSpecialRendererMixin"
	],
	"injectors": {
		"defaultRequire": 1
	}
}
